setup.py
legos/__init__.py
legos/couragewolf.py
legos.couragewolf.egg-info/PKG-INFO
legos.couragewolf.egg-info/SOURCES.txt
legos.couragewolf.egg-info/dependency_links.txt
legos.couragewolf.egg-info/namespace_packages.txt
legos.couragewolf.egg-info/requires.txt
legos.couragewolf.egg-info/top_level.txt