Metadata-Version: 1.1
Name: legos.couragewolf
Version: 0.1.0
Summary: A lego that grabs a single random line from a provided file and returns it to Legobot for handling when it spots the words "encourage me" in a message
Home-page: https://github.com/bbriggs/legos.couragewolf
Author: Brenton Briggs II
Author-email: UNKNOWN
License: GPLv3
Platform: UNKNOWN
Classifier: License :: OSI Approved :: GNU General Public License v3 (GPLv3)
Classifier: Programming Language :: Python :: 3
